pyapproxmc.cpython-38-x86_64-linux-gnu.so
pyapproxmc-4.1.24.dist-info/top_level.txt
pyapproxmc-4.1.24.dist-info/WHEEL
pyapproxmc-4.1.24.dist-info/RECORD
pyapproxmc-4.1.24.dist-info/LICENSE
pyapproxmc-4.1.24.dist-info/METADATA
