Metadata-Version: 2.1
Name: pyapproxmc
Version: 4.1.24
Summary: Bindings to ApproxMC, an approximate model counter
Home-page: https://github.com/meelgroup/approxmc
Author-email: Mate Soos <soos.mate@gmail.com>
Maintainer-email: Mate Soos <soos.mate@gmail.com>
License: MIT License
Keywords: sat,model-counting
Classifier: Development Status :: 4 - Beta
Classifier: Intended Audience :: Developers
Classifier: Operating System :: OS Independent
Classifier: Programming Language :: C++
Classifier: Programming Language :: Python :: 3
Classifier: Programming Language :: Python :: 3.5
Classifier: License :: OSI Approved :: MIT License
Classifier: Topic :: Utilities
Requires-Python: >=3.5
License-File: LICENSE
